naruto_skills/__init__.py
naruto_skills/dataset.py
naruto_skills/dataset_test.py
naruto_skills/dataset_v2.py
naruto_skills/dataset_v2_demo.py
naruto_skills/dl_logging.py
naruto_skills/dl_logging_demo.py
naruto_skills/graph_utils.py
naruto_skills/network.py
naruto_skills/new_voc.py
naruto_skills/predictor.py
naruto_skills/pytorch_utils.py
naruto_skills/solr.py
naruto_skills/text_transformer.py
naruto_skills/trainer.py
naruto_skills/training_checker.py
naruto_skills/voc.py
naruto_skills/voc_test.py
naruto_skills/vocab_builder.py
naruto_skills/word_embedding.py
naruto_skills-1.2.dist-info/METADATA
naruto_skills-1.2.dist-info/RECORD
naruto_skills-1.2.dist-info/WHEEL
naruto_skills-1.2.dist-info/top_level.txt
