Metadata-Version: 2.1
Name: naruto-skills
Version: 1.2
Summary: Naruto has to do some tasks very quickly. The lib helps him to deal with those tremendous tasks
Home-page: UNKNOWN
Author: Duc Tri Nguyen
Author-email: ductricse@gmail.com
License: MIT
Platform: UNKNOWN
Classifier: Programming Language :: Python :: 3.5
Classifier: Programming Language :: Python :: 3.6
